[
  {"Rank":"1","Language":"Mandarin Chinese"},
  {"Rank":"2","Language":"Spanish"},
  {"Rank":"3","Language":"English"},
  {"Rank":"4","Language":"Hindi(Sanskritised Hindustani)"},
  {"Rank":"5","Language":"Bengali"},
  {"Rank":"6","Language":"Portuguese"},
  {"Rank":"7","Language":"Russian"},
  {"Rank":"8","Language":"Japanese"},
  {"Rank":"9","Language":"Western Punjabi"},
  {"Rank":"10","Language":"Marathi"},
  {"Rank":"11","Language":"Telugu"},
  {"Rank":"12","Language":"Wu Chinese"},
  {"Rank":"13","Language":"Turkish"},
  {"Rank":"14","Language":"Korean"},
  {"Rank":"15","Language":"French"},
  {"Rank":"16","Language":"German"},
  {"Rank":"17","Language":"Vietnamese"},
  {"Rank":"18","Language":"Tamil"},
  {"Rank":"19","Language":"Yue Chinese"},
  {"Rank":"20","Language":"Urdu(Persianised Hindustani)"},
  {"Rank":"21","Language":"Javanese"},
  {"Rank":"22","Language":"Italian"},
  {"Rank":"23","Language":"Egyptian Arabic"},
  {"Rank":"24","Language":"Gujarati"},
  {"Rank":"25","Language":"Iranian Persian"},
  {"Rank":"26","Language":"Bhojpuri"},
  {"Rank":"27","Language":"Min Nan Chinese"},
  {"Rank":"28","Language":"Hakka Chinese"},
  {"Rank":"29","Language":"Jin Chinese"},
  {"Rank":"30","Language":"Hausa"},
  {"Rank":"31","Language":"Kannada"},
  {"Rank":"32","Language":"Indonesian(Indonesian Malay)"},
  {"Rank":"33","Language":"Polish"},
  {"Rank":"34","Language":"Yoruba"},
  {"Rank":"35","Language":"Xiang Chinese"},
  {"Rank":"36","Language":"Malayalam"},
  {"Rank":"37","Language":"Odia"},
  {"Rank":"38","Language":"Maithili"},
  {"Rank":"39","Language":"Burmese"},
  {"Rank":"40","Language":"Eastern Punjabi"},
  {"Rank":"41","Language":"Sunda"},
  {"Rank":"42","Language":"Sudanese Arabic"},
  {"Rank":"43","Language":"Algerian Arabic"},
  {"Rank":"44","Language":"Moroccan Arabic"},
  {"Rank":"45","Language":"Ukrainian"},
  {"Rank":"46","Language":"Igbo"},
  {"Rank":"47","Language":"Northern Uzbek"},
  {"Rank":"48","Language":"Sindhi"},
  {"Rank":"49","Language":"North Levantine Arabic"},
  {"Rank":"50","Language":"Romanian"},
  {"Rank":"51","Language":"Tagalog"},
  {"Rank":"52","Language":"Dutch"},
  {"Rank":"53","Language":"Saʽidi Arabic"},
  {"Rank":"54","Language":"Gan Chinese"},
  {"Rank":"55","Language":"Amharic"},
  {"Rank":"56","Language":"Northern Pashto"},
  {"Rank":"57","Language":"Magahi"},
  {"Rank":"58","Language":"Thai"},
  {"Rank":"59","Language":"Saraiki"},
  {"Rank":"60","Language":"Khmer"},
  {"Rank":"61","Language":"Chhattisgarhi"},
  {"Rank":"62","Language":"Somali"},
  {"Rank":"63","Language":"Malay (Malaysian Malay)"},
  {"Rank":"64","Language":"Cebuano"},
  {"Rank":"65","Language":"Nepali"},
  {"Rank":"66","Language":"Mesopotamian Arabic"},
  {"Rank":"67","Language":"Assamese"},
  {"Rank":"68","Language":"Sinhalese"},
  {"Rank":"69","Language":"Northern Kurdish"},
  {"Rank":"70","Language":"Hejazi Arabic"},
  {"Rank":"71","Language":"Nigerian Fulfulde"},
  {"Rank":"72","Language":"Bavarian"},
  {"Rank":"73","Language":"South Azerbaijani"},
  {"Rank":"74","Language":"Greek"},
  {"Rank":"75","Language":"Chittagonian"},
  {"Rank":"76","Language":"Kazakh"},
  {"Rank":"77","Language":"Deccan"},
  {"Rank":"78","Language":"Hungarian"},
  {"Rank":"79","Language":"Kinyarwanda"},
  {"Rank":"80","Language":"Zulu"},
  {"Rank":"81","Language":"South Levantine Arabic"},
  {"Rank":"82","Language":"Tunisian Arabic"},
  {"Rank":"83","Language":"Sanaani Spoken Arabic"},
  {"Rank":"84","Language":"Min Bei Chinese"},
  {"Rank":"85","Language":"Southern Pashto"},
  {"Rank":"86","Language":"Rundi"},
  {"Rank":"87","Language":"Czech"},
  {"Rank":"88","Language":"Taʽizzi-Adeni Arabic"},
  {"Rank":"89","Language":"Uyghur"},
  {"Rank":"90","Language":"Min Dong Chinese"},
  {"Rank":"91","Language":"Sylheti"}
]
